pp7stubs/__init__.py
pp7stubs/action_pb2.py
pp7stubs/action_pb2.pyi
pp7stubs/alignmentGuide_pb2.py
pp7stubs/alignmentGuide_pb2.pyi
pp7stubs/alphaType_pb2.py
pp7stubs/alphaType_pb2.pyi
pp7stubs/analyticsApi_pb2.py
pp7stubs/analyticsApi_pb2.pyi
pp7stubs/analyticsCapture_pb2.py
pp7stubs/analyticsCapture_pb2.pyi
pp7stubs/analyticsCreate_pb2.py
pp7stubs/analyticsCreate_pb2.pyi
pp7stubs/analyticsEvent_pb2.py
pp7stubs/analyticsEvent_pb2.pyi
pp7stubs/analyticsImport_pb2.py
pp7stubs/analyticsImport_pb2.pyi
pp7stubs/analyticsMultiTracks_pb2.py
pp7stubs/analyticsMultiTracks_pb2.pyi
pp7stubs/analyticsPlaybackMarker_pb2.py
pp7stubs/analyticsPlaybackMarker_pb2.pyi
pp7stubs/analyticsProContent_pb2.py
pp7stubs/analyticsProContent_pb2.pyi
pp7stubs/analyticsStartup_pb2.py
pp7stubs/analyticsStartup_pb2.pyi
pp7stubs/analyticsSync_pb2.py
pp7stubs/analyticsSync_pb2.pyi
pp7stubs/analyticsTimecode_pb2.py
pp7stubs/analyticsTimecode_pb2.pyi
pp7stubs/analyticsTimeline_pb2.py
pp7stubs/analyticsTimeline_pb2.pyi
pp7stubs/analyticsTriggerMedia_pb2.py
pp7stubs/analyticsTriggerMedia_pb2.pyi
pp7stubs/analyticsTrigger_pb2.py
pp7stubs/analyticsTrigger_pb2.pyi
pp7stubs/analyticsUI_pb2.py
pp7stubs/analyticsUI_pb2.pyi
pp7stubs/analyticsUpdate_pb2.py
pp7stubs/analyticsUpdate_pb2.pyi
pp7stubs/analyticsWHMStore_pb2.py
pp7stubs/analyticsWHMStore_pb2.pyi
pp7stubs/applicationInfo_pb2.py
pp7stubs/applicationInfo_pb2.pyi
pp7stubs/audio_pb2.py
pp7stubs/audio_pb2.pyi
pp7stubs/background_pb2.py
pp7stubs/background_pb2.pyi
pp7stubs/baseDocument_pb2.py
pp7stubs/baseDocument_pb2.pyi
pp7stubs/calendar_pb2.py
pp7stubs/calendar_pb2.pyi
pp7stubs/ccli_pb2.py
pp7stubs/ccli_pb2.pyi
pp7stubs/clearGroups_pb2.py
pp7stubs/clearGroups_pb2.pyi
pp7stubs/collectionElementType_pb2.py
pp7stubs/collectionElementType_pb2.pyi
pp7stubs/color_pb2.py
pp7stubs/color_pb2.pyi
pp7stubs/cue_pb2.py
pp7stubs/cue_pb2.pyi
pp7stubs/digitalAudio_pb2.py
pp7stubs/digitalAudio_pb2.pyi
pp7stubs/dmxProfiles_pb2.py
pp7stubs/dmxProfiles_pb2.pyi
pp7stubs-7.16.2.dist-info/LICENSE
pp7stubs-7.16.2.dist-info/METADATA
pp7stubs-7.16.2.dist-info/WHEEL
pp7stubs-7.16.2.dist-info/top_level.txt
pp7stubs-7.16.2.dist-info/RECORD
