Metadata-Version: 2.1
Name: pp7stubs
Version: 7.16.2
Summary: Python code generated by protoc from ProPresenter 7 proto files, modified to use explicit relative imports.
Author: 2esword
License: MIT License
Project-URL: Repository, https://github.com/2esword/pp7stubs
Requires-Python: >=3.8
License-File: LICENSE
Requires-Dist: protobuf >=5.27.1
